setup.cfg
setup.py
pywesome/__init__.py
pywesome/collection.py
pywesome/pywesome.py
pywesome.egg-info/PKG-INFO
pywesome.egg-info/SOURCES.txt
pywesome.egg-info/dependency_links.txt
pywesome.egg-info/top_level.txt