Metadata-Version: 1.1
Name: pywesome
Version: 1.0.2
Summary: Python lists on steroidss
Home-page: https://github.com/lucasbedout/pywesome
Author: Lucas Bedout
Author-email: roadtostark@gmail.com
License: UNKNOWN
Download-URL: https://github.com/lucasbedout/pywesome/tarball/v1.0.2
Keywords: list,collection,map,reduce,filter
Platform: UNKNOWN
